boto3_dataclass_ses/__init__.py
boto3_dataclass_ses/caster.py
boto3_dataclass_ses/type_defs.py
boto3_dataclass_ses-1.40.0.dist-info/LICENSE.txt
boto3_dataclass_ses-1.40.0.dist-info/METADATA
boto3_dataclass_ses-1.40.0.dist-info/WHEEL
boto3_dataclass_ses-1.40.0.dist-info/RECORD
