Metadata-Version: 2.3
Name: boto3_dataclass_ses
Version: 1.40.0
Summary: Dataclass for boto3 ses.
License: MIT
Author: Sanhe Hu
Author-email: husanhe@email.com
Maintainer: Sanhe Hu
Maintainer-email: husanhe@email.com
Requires-Python: >=3.10,<4.0
Classifier: License :: OSI Approved :: MIT License
Classifier: Programming Language :: Python :: 3
Classifier: Programming Language :: Python :: 3.10
Classifier: Programming Language :: Python :: 3.11
Classifier: Programming Language :: Python :: 3.12
Classifier: Programming Language :: Python :: 3.13
Requires-Dist: mypy-boto3-ses (>=1.40.0,<1.41.0)
Requires-Dist: typing-extensions ; python_version < "3.12"
Project-URL: Documentation, https://boto3-dataclass.readthedocs.io/en/latest/
Project-URL: Download, https://pypi.org/pypi/boto3-dataclass-ses#files
Project-URL: Homepage, https://github.com/MacHu-GWU/boto3_dataclass-project
Project-URL: Issues, https://github.com/MacHu-GWU/boto3_dataclass-project/issues
Project-URL: Repository, https://github.com/MacHu-GWU/boto3_dataclass-project
